flame_lib/__init__.py
flame_lib/flamegame.py
flame_lib-0.1.0.dist-info/METADATA
flame_lib-0.1.0.dist-info/WHEEL
flame_lib-0.1.0.dist-info/top_level.txt
flame_lib-0.1.0.dist-info/RECORD
