Metadata-Version: 2.1
Name: flame-lib
Version: 0.1.0
Summary: Demo library
Home-page: https://flame-lib.readthedocs.io/
Author: 
Author-email: example@email.com
Classifier: Intended Audience :: Developers
Classifier: License :: OSI Approved :: MIT License
Classifier: Programming Language :: Python
Classifier: Programming Language :: Python :: 3
Classifier: Programming Language :: Python :: 3.6
Classifier: Programming Language :: Python :: 3.7
Classifier: Programming Language :: Python :: 3.8
Classifier: Programming Language :: Python :: 3.9
Classifier: Operating System :: OS Independent
